ssh_negotiate_term.py
ssh_negotiate_term-0.0.2.dist-info/LICENSE
ssh_negotiate_term-0.0.2.dist-info/METADATA
ssh_negotiate_term-0.0.2.dist-info/WHEEL
ssh_negotiate_term-0.0.2.dist-info/entry_points.txt
ssh_negotiate_term-0.0.2.dist-info/top_level.txt
ssh_negotiate_term-0.0.2.dist-info/RECORD
