Metadata-Version: 2.1
Name: ssh-negotiate-term
Version: 0.0.2
Summary: Downgrade TERM strings when connecting to selected SSH servers
Author-email: Tom Ryder <tom@sanctum.geek.nz>
Project-URL: Homepage, https://sanctum.geek.nz/
Project-URL: Source, https://dev.sanctum.geek.nz/cgit/ssh_negotiate_term.git/
Classifier: Programming Language :: Python :: 3
Classifier: License :: OSI Approved :: GNU General Public License v3 or later (GPLv3+)
Classifier: Operating System :: OS Independent
Requires-Python: >=3.7
License-File: LICENSE
